{
  "passed": 18,
  "failed": 0,
  "all_passed": true,
  "results": [
    {
      "id": 1,
      "name": "csv_exists",
      "category": "存在",
      "status": "PASS",
      "detail": "",
      "fix_hint": ""
    },
    {
      "id": 2,
      "name": "row_count_min",
      "category": "網羅性",
      "status": "PASS",
      "detail": "",
      "fix_hint": ""
    },
    {
      "id": 3,
      "name": "required_columns",
      "category": "スキーマ",
      "status": "PASS",
      "detail": "",
      "fix_hint": ""
    },
    {
      "id": 4,
      "name": "session_date_no_null",
      "category": "完全性",
      "status": "PASS",
      "detail": "",
      "fix_hint": ""
    },
    {
      "id": 5,
      "name": "session_date_format",
      "category": "値域",
      "status": "PASS",
      "detail": "",
      "fix_hint": ""
    },
    {
      "id": 6,
      "name": "instructor_id_no_null",
      "category": "完全性",
      "status": "PASS",
      "detail": "",
      "fix_hint": ""
    },
    {
      "id": 7,
      "name": "instructor_id_variety",
      "category": "網羅性",
      "status": "PASS",
      "detail": "",
      "fix_hint": ""
    },
    {
      "id": 8,
      "name": "specialty_variety",
      "category": "網羅性",
      "status": "PASS",
      "detail": "",
      "fix_hint": ""
    },
    {
      "id": 9,
      "name": "employment_type_variety",
      "category": "網羅性",
      "status": "PASS",
      "detail": "",
      "fix_hint": ""
    },
    {
      "id": 10,
      "name": "lesson_count_positive",
      "category": "値域",
      "status": "PASS",
      "detail": "",
      "fix_hint": ""
    },
    {
      "id": 11,
      "name": "lesson_count_max4",
      "category": "値域",
      "status": "PASS",
      "detail": "",
      "fix_hint": ""
    },
    {
      "id": 12,
      "name": "hourly_rate_positive",
      "category": "値域",
      "status": "PASS",
      "detail": "",
      "fix_hint": ""
    },
    {
      "id": 13,
      "name": "attendee_count_positive",
      "category": "値域",
      "status": "PASS",
      "detail": "",
      "fix_hint": ""
    },
    {
      "id": 14,
      "name": "lesson_cost_positive",
      "category": "値域",
      "status": "PASS",
      "detail": "",
      "fix_hint": ""
    },
    {
      "id": 15,
      "name": "workload_flag_values",
      "category": "値域",
      "status": "PASS",
      "detail": "",
      "fix_hint": ""
    },
    {
      "id": 16,
      "name": "source_file_no_null",
      "category": "完全性",
      "status": "PASS",
      "detail": "",
      "fix_hint": ""
    },
    {
      "id": 17,
      "name": "lesson_hours_calculation",
      "category": "計算整合性",
      "status": "PASS",
      "detail": "",
      "fix_hint": ""
    },
    {
      "id": 18,
      "name": "null_rate_all_cols",
      "category": "品質",
      "status": "PASS",
      "detail": "",
      "fix_hint": ""
    }
  ]
}